wingman_run/__init__.py
wingman_run/client.py
wingman_run/macos_helper.py
wingman_run-0.1.2.dist-info/METADATA
wingman_run-0.1.2.dist-info/WHEEL
wingman_run-0.1.2.dist-info/entry_points.txt
wingman_run-0.1.2.dist-info/top_level.txt
wingman_run-0.1.2.dist-info/RECORD
