Metadata-Version: 2.4
Name: wingman-run
Version: 0.1.2
Summary: Simple text replacer that replaces 'helloworld' with 'Hello World!' using a global hotkey
Author-email: Your Name <your.email@example.com>
Project-URL: Homepage, https://wingman.run
Project-URL: Repository, https://github.com/yourusername/wingman
Project-URL: Issues, https://github.com/yourusername/wingman/issues
Keywords: text,replacement,hotkey,automation,macos
Classifier: Development Status :: 3 - Alpha
Classifier: Environment :: MacOS X
Classifier: Intended Audience :: End Users/Desktop
Classifier: Operating System :: MacOS
Classifier: Programming Language :: Python :: 3
Classifier: Programming Language :: Python :: 3.10
Classifier: Programming Language :: Python :: 3.11
Classifier: Programming Language :: Python :: 3.12
Classifier: Topic :: Text Processing :: Linguistic
Classifier: Topic :: Utilities
Classifier: License :: Other/Proprietary License
Requires-Python: >=3.10
Requires-Dist: requests>=2.32
Requires-Dist: pyautogui==0.9.54
Requires-Dist: pyperclip>=1.9
Requires-Dist: python-dotenv>=1.0
Requires-Dist: sseclient-py>=1.8
Requires-Dist: pynput>=1.7.6
Requires-Dist: click>=8.1.0
Requires-Dist: pyobjc-framework-Quartz>=9.0; sys_platform == "darwin"
Requires-Dist: pyobjc-framework-ApplicationServices>=9.0; sys_platform == "darwin"
Requires-Dist: pyobjc-framework-Cocoa>=9.0; sys_platform == "darwin"
